pomodoro_calculator/__init__.py
pomodoro_calculator/main.py
pomodoro_calculator/test/__init__.py
pomodoro_calculator/test/test_main.py
pomodoro_calculator-1.0.4.dist-info/LICENCE
pomodoro_calculator-1.0.4.dist-info/METADATA
pomodoro_calculator-1.0.4.dist-info/WHEEL
pomodoro_calculator-1.0.4.dist-info/entry_points.txt
pomodoro_calculator-1.0.4.dist-info/top_level.txt
pomodoro_calculator-1.0.4.dist-info/RECORD
