Metadata-Version: 2.1
Name: pomodoro-calculator
Version: 1.0.4
Summary: A pretty command line tool to calculate the number of Pomodori available between two points in time.
Home-page: https://codeberg.org/Dokana/Pomodoro-Calculator
Author: Matt Deacalion Stevens
Author-email: matt@dirtymonkey.co.uk
License: ISC
Keywords: pomodoro productivity timer freelance freelancing
Classifier: Development Status :: 4 - Beta
Classifier: Environment :: Console
Classifier: Intended Audience :: Developers
Classifier: Intended Audience :: End Users/Desktop
Classifier: License :: OSI Approved :: ISC License (ISCL)
Classifier: Natural Language :: English
Classifier: Operating System :: POSIX :: Linux
Classifier: Operating System :: POSIX :: BSD
Classifier: Programming Language :: Python :: 2.7
Classifier: Programming Language :: Python :: 3.2
Classifier: Programming Language :: Python :: 3.3
Classifier: Programming Language :: Python :: 3.4
Classifier: Topic :: Office/Business :: Scheduling
Classifier: Topic :: Utilities
License-File: LICENCE
Requires-Dist: colorama (>=0.3.1)
Requires-Dist: docopt (>=0.6.1)
